Workbook

Sheet Calculator
A1: Confusion Matrix Interactive Calculator v. 1.0
A2: Method and Design by Meni Berger Data Ninja ©
B3: Tel. 0522834241 | C3: Dataninjapro@gmail.com | D3: 0522 834 241
B6: User Inputs: | C6: True Negative (TN): | D6: 350
C7: False Positive (FP): | D7: 6
C8: False Negative (FN): | D8: 100
C9: True Positive (TP): | D9: 15
B13: Observed \ Predicted | C13: Negative | D13: Positive
B14: Negative | C14: TN | D14: FP
B15: Positive | C15: FN | D15: TP
B17: Metric | C17: Formula | D17: Value | E17: Status
B18: Sensitivity | C18: TP / (TP+FN) | D18: =IF((D9+D8)=0,"N/A",D9/(D9+D8)) -> 0.13043478 | E18: =IF(D18="N/A","Undefined",IF(D18>=0.9,"Excellent",IF(D18>=0.8,"Good",IF(D18>=0.7,"Moderate","Low")))) -> Low
B19: Specificity | C19: TN / (TN+FP) | D19: =IF((D6+D7)=0,"N/A",D6/(D6+D7)) -> 0.98314607 | E19: =IF(D19="N/A","Undefined",IF(D19>=0.9,"Excellent",IF(D19>=0.8,"Good",IF(D19>=0.7,"Moderate","Low")))) -> Excellent
B20: Precision (PPV) | C20: TP / (TP+FP) | D20: =IF((D9+D7)=0,"N/A",D9/(D9+D7)) -> 0.71428571 | E20: =IF(D20="N/A","Undefined",IF(D20>=0.9,"Excellent",IF(D20>=0.8,"Good",IF(D20>=0.7,"Moderate","Low")))) -> Moderate
B21: NPV | C21: TN / (TN+FN) | D21: =IF((D6+D8)=0,"N/A",D6/(D6+D8)) -> 0.77777778 | E21: =IF(D21="N/A","Undefined",IF(D21>=0.9,"Excellent",IF(D21>=0.8,"Good",IF(D21>=0.7,"Moderate","Low")))) -> Moderate
B22: Accuracy | C22: (TP+TN) / Total | D22: =IF(SUM(D6:D9)=0,"N/A",(D9+D6)/SUM(D6:D9)) -> 0.77494692 | E22: =IF(D22="N/A","Undefined",IF(D22>=0.9,"Excellent",IF(D22>=0.8,"Good",IF(D22>=0.7,"Moderate","Low")))) -> Moderate
B23: FPR | C23: FP / (FP+TN) | D23: =IF((D7+D6)=0,"N/A",D7/(D7+D6)) -> 0.016853933 | E23: =IF(D23="N/A","Undefined",IF(D23<=0.1,"Excellent",IF(D23<=0.2,"Good",IF(D23<=0.3,"Moderate","Low")))) -> Excellent
B24: FNR | C24: FN / (FN+TP) | D24: =IF((D8+D9)=0,"N/A",D8/(D8+D9)) -> 0.86956522 | E24: =IF(D24="N/A","Undefined",IF(D24<=0.1,"Excellent",IF(D24<=0.2,"Good",IF(D24<=0.3,"Moderate","Low")))) -> Low
B25: Bal. Accuracy | C25: (Sensitivity+Specificity)/2 | D25: =IF(OR((D9+D8)=0,(D6+D7)=0),"N/A",((D9/(D9+D8))+(D6/(D6+D7)))/2) -> 0.55679043 | E25: =IF(D25="N/A","Undefined",IF(D25>=0.9,"Excellent",IF(D25>=0.8,"Good",IF(D25>=0.7,"Moderate","Low")))) -> Low
B26: F1 Score | C26: 2TP / (2TP+FP+FN) | D26: =IF((2*D9+D7+D8)=0,"N/A",(2*D9)/(2*D9+D7+D8)) -> 0.22058824 | E26: =IF(D26="N/A","Undefined",IF(D26>=0.9,"Excellent",IF(D26>=0.8,"Good",IF(D26>=0.7,"Moderate","Low")))) -> Low
B27: Cohen’s Kappa | C27: Agreement corrected for chance | D27: =Calc_Backend!B9 -> 0.15702563 | E27: =IF(D27="N/A","Undefined",IF(D27>=0.6,"Excellent",IF(D27>=0.4,"Good",IF(D27>=0.2,"Moderate","Low")))) -> Low
D28: Protected template | Editable input cells only
B30: This tool is intended to support interpretation of classification metrics. Metrics should be considered together and interpreted in the context of the data structure, class balance, and the model’s intended use.

Sheet Method
A1: Confusion Matrix Metrics Interpretation Guide
A2: =HYPERLINK("#Calculator!A1","Back to Calculator") -> Back to Calculator
A3: This sheet provides concise explanations for the performance metrics used in the Confusion Matrix Interactive Calculator.
A5: Sensitivity (Recall)
A6: TP / (TP + FN)
A7: Sensitivity measures the proportion of actual positive cases that the model correctly identifies out of all cases that are positive in reality.
A8: A high sensitivity indicates that the model is good at detecting the target class (1) and therefore misses fewer true positive cases.
A9: A low sensitivity indicates that the model misses a substantial proportion of actual positive cases, meaning that its False Negative rate is relatively high.
A10: Sensitivity is especially important when missing a positive case carries a meaningful cost or risk.
A12: Specificity
A13: TN / (TN + FP)
A14: Specificity measures the proportion of actual negative cases that the model correctly identifies out of all cases that are negative in reality (0).
A15: A high specificity indicates that the model is good at identifying negative cases and therefore produces fewer false positive results.
A16: A low specificity indicates that the model tends to classify negative cases as positive, meaning that its False Positive rate is relatively high.
... A79: • The metrics in this calculator are intended to support interpretation and do not replace professional judgment.

Sheet Calc_Backend
A1: Kappa labels | B1: Kappa Values and Formulas
A2: Total N | B2: =SUM(Calculator!D6:D9) -> 471
A3: Observed agreement (Po) | B3: =IF(B2=0,"N/A",(Calculator!D6+Calculator!D9)/B2) -> 0.77494692
A4: Row total negative | B4: =Calculator!D6+Calculator!D7 -> 356
A5: Row total positive | B5: =Calculator!D8+Calculator!D9 -> 115
A6: Column total negative | B6: =Calculator!D6+Calculator!D8 -> 450
A7: Column total positive | B7: =Calculator!D7+Calculator!D9 -> 21
A8: Expected agreement (Pe) | B8: =IF(B2=0,"N/A",((B4*B6)+(B5*B7))/(B2^2)) -> 0.733025
A9: Kappa | B9: =IF(OR(B3="N/A",B8="N/A",1-B8=0),"N/A",(B3-B8)/(1-B8)) -> 0.15702563
